aiowhitebit_mcp/__init__.py
aiowhitebit_mcp/cache.py
aiowhitebit_mcp/circuit_breaker.py
aiowhitebit_mcp/cli.py
aiowhitebit_mcp/client.py
aiowhitebit_mcp/metrics.py
aiowhitebit_mcp/monitoring.py
aiowhitebit_mcp/proxy.py
aiowhitebit_mcp/rate_limiter.py
aiowhitebit_mcp/server.py
aiowhitebit_mcp/types.py
aiowhitebit_mcp/web_interface.py
aiowhitebit_mcp-0.3.0.dist-info/licenses/LICENSE
aiowhitebit_mcp-0.3.0.dist-info/METADATA
aiowhitebit_mcp-0.3.0.dist-info/WHEEL
aiowhitebit_mcp-0.3.0.dist-info/entry_points.txt
aiowhitebit_mcp-0.3.0.dist-info/top_level.txt
aiowhitebit_mcp-0.3.0.dist-info/RECORD
