Metadata-Version: 2.4
Name: aiowhitebit-mcp
Version: 0.3.0
Summary: MCP server and client for WhiteBit cryptocurrency exchange API
Home-page: https://github.com/doubledare704/aiowhitebit-mcp
Author: doubledare704
Author-email: doubledare704 <doubledare704@gmail.com>
License: Apache License 2.0
Project-URL: Homepage, https://github.com/doubledare704/aiowhitebit-mcp
Project-URL: Bug Tracker, https://github.com/doubledare704/aiowhitebit-mcp/issues
Project-URL: Documentation, https://github.com/doubledare704/aiowhitebit-mcp#readme
Project-URL: Source Code, https://github.com/doubledare704/aiowhitebit-mcp
Keywords: whitebit,cryptocurrency,exchange,api,mcp,claude
Classifier: Development Status :: 4 - Beta
Classifier: Intended Audience :: Developers
Classifier: License :: OSI Approved :: Apache Software License
Classifier: Programming Language :: Python :: 3
Classifier: Programming Language :: Python :: 3.10
Classifier: Programming Language :: Python :: 3.11
Classifier: Programming Language :: Python :: 3.12
Classifier: Topic :: Software Development :: Libraries :: Python Modules
Classifier: Topic :: Internet :: WWW/HTTP
Requires-Python: >=3.10
License-File: LICENSE
Requires-Dist: aiowhitebit==0.4.0
Requires-Dist: fastmcp==2.12.5
Requires-Dist: pydantic>=2.12.3
Requires-Dist: aiohttp>=3.13.1
Provides-Extra: dev
Requires-Dist: pytest>=8.4.2; extra == "dev"
Requires-Dist: pytest-asyncio>=1.2.0; extra == "dev"
Requires-Dist: pytest-cov>=7.0.0; extra == "dev"
Requires-Dist: ruff>=0.14.1; extra == "dev"
Requires-Dist: pyright>=1.1.406; extra == "dev"
Requires-Dist: pre-commit>=4.3.0; extra == "dev"
Dynamic: author
Dynamic: home-page
Dynamic: license-file
Dynamic: requires-python
